combalg/__init__.py
combalg/combalg.py
combalg/rooted_tree.py
combalg/subset.py
combalg/utility.py
combalg_py-0.0.3.dist-info/DESCRIPTION.rst
combalg_py-0.0.3.dist-info/METADATA
combalg_py-0.0.3.dist-info/RECORD
combalg_py-0.0.3.dist-info/WHEEL
combalg_py-0.0.3.dist-info/metadata.json
combalg_py-0.0.3.dist-info/top_level.txt
