Metadata-Version: 2.0
Name: combalg-py
Version: 0.0.3
Summary: combinatorial algorithms
Home-page: https://bitbucket.org/samstump/combalg-py
Author: Sam Stump
Author-email: sstump64@gmail.com
License: MIT
Platform: linux,win,osx
Classifier: Development Status :: 3 - Alpha
Classifier: Intended Audience :: Developers
Classifier: Intended Audience :: Education
Classifier: Intended Audience :: Science/Research
Classifier: License :: OSI Approved :: MIT License
Classifier: Natural Language :: English
Classifier: Operating System :: OS Independent
Classifier: Programming Language :: Python :: 3.5
Classifier: Topic :: Scientific/Engineering :: Mathematics
